pylogpoint/__init__.py
pylogpoint/low.py
pylogpoint-1.2.dist-info/DESCRIPTION.rst
pylogpoint-1.2.dist-info/METADATA
pylogpoint-1.2.dist-info/RECORD
pylogpoint-1.2.dist-info/WHEEL
pylogpoint-1.2.dist-info/metadata.json
pylogpoint-1.2.dist-info/top_level.txt
