Metadata-Version: 2.0
Name: pylogpoint
Version: 1.2
Summary: Interface to the LogPoint Search API
Home-page: https://bitbucket.org/gclinch/pylogpoint
Author: Graham Clinch
Author-email: g.clinch@lancaster.ac.uk
License: Apache License, Version 2.0
Platform: UNKNOWN
Classifier: Development Status :: 4 - Beta
Classifier: License :: OSI Approved :: Apache Software License
Requires-Dist: requests
